kd163PhotoDownloader/LICENSE
kd163PhotoDownloader/README.md
kd163PhotoDownloader/__init__.py
kd163PhotoDownloader/album.py
kd163PhotoDownloader/fileutil.py
kd163PhotoDownloader/kd163PhotoDownloader.py
kd163PhotoDownloader/kd163PhotoDownloader.ui
kd163PhotoDownloader/setup.py
kd163PhotoDownloader/doc/kd163PhotoDownloader_screenshot.png
kd163PhotoDownloader/doc/screen-2019-02-18-21-09-06.png
kd163PhotoDownloader/doc/screenshot-dfc607b6.png
kd163PhotoDownloader-1.0.1.dist-info/DESCRIPTION.rst
kd163PhotoDownloader-1.0.1.dist-info/METADATA
kd163PhotoDownloader-1.0.1.dist-info/RECORD
kd163PhotoDownloader-1.0.1.dist-info/WHEEL
kd163PhotoDownloader-1.0.1.dist-info/entry_points.txt
kd163PhotoDownloader-1.0.1.dist-info/metadata.json
kd163PhotoDownloader-1.0.1.dist-info/top_level.txt
kdLaunchPad/__init__.py
kdLaunchPad/fileutil.py
kdLaunchPad/kdLaunchPad.py
kdLaunchPad/kdconfig.py
kdLaunchPad/kdconfigutil.py
kdLaunchPad/launchSession.py
kdLaunchPad/sessionItem.py
kdLaunchPad/setup.py
