Metadata-Version: 2.0
Name: kd163PhotoDownloader
Version: 1.0.1
Summary: 网易相册下载工具
Home-page: https://github.com/bkdwei/kd163PhotoDownloader
Author: bkdwei
Author-email: bkdwei@163.com
Maintainer: 韦坤东
Maintainer-email: bkdwei@163.com
License: GPLv3+
Keywords: kd163PhotoDownloader,网易相册,网易云相册,下载
Platform: Windows
Platform: Linux
Classifier: Development Status :: 5 - Production/Stable
Classifier: Environment :: X11 Applications :: Qt
Classifier: Intended Audience :: End Users/Desktop
Classifier: Natural Language :: Chinese (Simplified)
Classifier: Topic :: Internet :: File Transfer Protocol (FTP)
Classifier: Programming Language :: Python :: 3
Classifier: License :: OSI Approved :: GNU General Public License v3 or later (GPLv3+)
Classifier: Operating System :: POSIX
Classifier: Operating System :: Microsoft :: Windows
Requires-Dist: PyQt5
